{
  "format_version":"1.10.0",
  "minecraft:client_entity":{
    "description":{
      "identifier":"pokemon:p239",
      "materials":{"default":"pokemon","aura":"aura"},
      "textures":{
    "evo_aura":"textures/entity/aura/evolve",
    "default":"textures/entity/normal/elekid",
    "default_s":"textures/entity/shiny/elekid",
    "mega1":"textures/entity/normal/elekid",
    "mega_s1":"textures/entity/shiny/elekid",
    "mega2":"textures/entity/normal/elekid",
    "mega_s2":"textures/entity/shiny/elekid",
    "gigamax":"textures/entity/normal/elekid",
    "gigamax_s":"textures/entity/shiny/elekid"
      },
      "geometry":{
    "default":"geometry.serpelekid",
    "mega1":"geometry.serpelekid",
    "mega2":"geometry.serpelekid",
    "gigamax":"geometry.serpelekid"
      },
      "animations":{
    "eyes_controller":"controller.animation.eyes",
    "open":"animation.serpmob.open",
    "close":"animation.serpmob.close",
    "angry":"animation.serpmob.angry",
    "fainted":"animation.serpmob.fainted",
    "quiet":"animation.elekid.quiet",
    "walk":"animation.elekid.walk",
    "sit":"animation.elekid.sitting",
    "attack":"animation.elekid.attack",
    "attack2":"animation.elekid.attack2",
    "defeated":"animation.elekid.defeated",
    "look_at_target":"animation.common.look_at_target",
    "main_controller":"controller.animation.pokemon_ground",
    "effects_controller":"controller.animation.effects"
      },
      "particle_effects":{
    "shiny":"serp:shiny"
      },
      "scripts":{
    "scale":"q.life_time<1?q.life_time*0.75:0.75",
    "animate":["effects_controller","main_controller"]
      },
      "render_controllers":["controller.render.pokemon","controller.render.aura"]
    }
  }
}