{
  "format_version":"1.10.0",
  "minecraft:client_entity":{
    "description":{
      "identifier":"pokemon:p241",
      "materials":{"default":"pokemon","aura":"aura"},
      "textures":{
    "evo_aura":"textures/entity/aura/evolve",
    "default":"textures/entity/normal/miltank",
    "default_s":"textures/entity/shiny/miltank",
    "mega1":"textures/entity/normal/miltank",
    "mega_s1":"textures/entity/shiny/miltank",
    "mega2":"textures/entity/normal/miltank",
    "mega_s2":"textures/entity/shiny/miltank",
    "gigamax":"textures/entity/normal/miltank",
    "gigamax_s":"textures/entity/shiny/miltank"
      },
      "geometry":{
    "default":"geometry.serpmiltank",
    "mega1":"geometry.serpmiltank",
    "mega2":"geometry.serpmiltank",
    "gigamax":"geometry.serpmiltank"
      },
      "animations":{
    "eyes_controller":"controller.animation.eyes",
    "open":"animation.serpmob.open",
    "close":"animation.serpmob.close",
    "angry":"animation.serpmob.angry",
    "fainted":"animation.serpmob.fainted",
    "quiet":"animation.miltank.quiet",
    "walk":"animation.miltank.walk",
    "sit":"animation.miltank.sitting",
    "attack":"animation.miltank.attack",
    "attack2":"animation.miltank.attack2",
    "defeated":"animation.miltank.defeated",
    "look_at_target":"animation.common.look_at_target",
    "main_controller":"controller.animation.pokemon_ground",
    "effects_controller":"controller.animation.effects"
      },
      "particle_effects":{
    "shiny":"serp:shiny"
      },
      "scripts":{
    "scale":"q.life_time<1?q.life_time*1.2:1.2",
    "animate":["effects_controller","main_controller"]
      },
      "render_controllers":["controller.render.pokemon","controller.render.aura"]
    }
  }
}