{
  "format_version":"1.10.0",
  "minecraft:client_entity":{
    "description":{
      "identifier":"pokemon:p725",
      "materials":{"default":"pokemon","aura":"aura"},
      "textures":{
    "evo_aura":"textures/entity/aura/evolve",
    "default":"textures/entity/normal/litten",
    "default_s":"textures/entity/shiny/litten",
    "mega1":"textures/entity/normal/litten",
    "mega_s1":"textures/entity/shiny/litten",
    "mega2":"textures/entity/normal/litten",
    "mega_s2":"textures/entity/shiny/litten",
    "gigamax":"textures/entity/normal/litten",
    "gigamax_s":"textures/entity/shiny/litten"
      },
      "geometry":{
    "default":"geometry.serplitten",
    "mega1":"geometry.serplitten",
    "mega2":"geometry.serplitten",
    "gigamax":"geometry.serplitten"
      },
      "animations":{
    "eyes_controller":"controller.animation.eyes",
    "open":"animation.serpmob.open",
    "close":"animation.serpmob.close",
    "angry":"animation.serpmob.angry",
    "fainted":"animation.serpmob.fainted",
    "quiet":"animation.litten.quiet",
    "walk":"animation.litten.walk",
    "sit":"animation.litten.sitting",
    "attack":"animation.litten.attack",
    "attack2":"animation.litten.attack2",
    "defeated":"animation.litten.defeated",
    "main_controller":"controller.animation.pokemon_ground",
    "effects_controller":"controller.animation.effects"
      },
      "particle_effects":{
    "shiny":"serp:shiny"
      },
      "scripts":{
    "scale":"q.life_time<1?q.life_time*1:1",
    "animate":["effects_controller","main_controller"]
      },
      "render_controllers":["controller.render.pokemon","controller.render.aura"]
    }
  }
}